README.rst
setup.py
lmfgg/__init__.py
lmfgg/common.py
lmfgg/test.py
lmfgg/txt.py
lmfgg.egg-info/PKG-INFO
lmfgg.egg-info/SOURCES.txt
lmfgg.egg-info/dependency_links.txt
lmfgg.egg-info/requires.txt
lmfgg.egg-info/top_level.txt
lmfgg/data/__init__.py
lmfgg/data/mytime.py
lmfgg/data/name.py
lmfgg/data/price.py
lmfgg/data/remi.py
lmfgg/getdata/__init__.py
lmfgg/getdata/words.txt
lmfgg/ps/__init__.py
lmfgg/ps/common.py
lmfgg/ps/psdata.py
lmfgg/ps/pspre.py
lmfgg/ps/worddict.txt
lmfgg/quyu/__init__.py
lmfgg/table/__init__.py
lmfgg/table/common.py
lmfgg/table/tbdata.py
lmfgg/table/tbpre.py
lmfgg/zz/__init__.py
lmfgg/zz/qiye.py
lmfgg/zz/ry.py